4-bit ALU/alu_4bit.v
module alu_4bit(

input [3:0] a,
input [3:0] b,
input [1:0] sel,
output reg [4:0] result // 5-bit to hold carry/borrow in ADD/SUB

);

always @(*) begin

case (sel)

2'b00: result = a & b;
2'b01: result = a | b;
2'b10: result = a + b;
2'b11: result = a - b;
default: result = 5'b00000;

endcase
end
endmodule

4-bit ALU/alu_4bit_tb.v
`timescale 1ns/100ps;

module alu_4bit_tb;

reg [3:0] a, b;
reg [1:0] sel;
wire [4:0] result;

alu_4bit dut(

.a(a),
.b(b),
.sel(sel),
.result(result)

);

initial begin

$dumpfile("test_alu_4bit.vcd");
$dumpvars(0, alu_4bit_tb);

    // Test vectors    

    // AND
    sel = 2'b00;
    a = 4'b1100; b = 4'b1010; #5;
    a = 4'b1111; b = 4'b0000; #5;

    // OR
    sel = 2'b01;
    a = 4'b1100; b = 4'b1010; #5;
    a = 4'b1111; b = 4'b0000; #5;

    // ADD
    sel = 2'b10;
    a = 4'b0011; b = 4'b0101; #5;  // 3 + 5 = 8
    a = 4'b1111; b = 4'b0001; #5;  // 15 + 1 = 16

    // SUB
    sel = 2'b11;
    a = 4'b1000; b = 4'b0011; #5;  // 8 - 3 = 5
    a = 4'b0001; b = 4'b0010; #5;  // 1 - 2 = -1 (in 2's complement = 5'b11111)

    #10 $finish;
end

endmodule

4-bit ALU/test_alu_4bit.vcd
$date
	Wed May  7 19:22:30 2025
$end
$version
	Icarus Verilog
$end
$timescale
	100ps
$end
$scope module alu_4bit_tb $end
$var wire 5 ! result [4:0] $end
$var reg 4 " a [3:0] $end
$var reg 4 # b [3:0] $end
$var reg 2 $ sel [1:0] $end
$scope module dut $end
$var wire 4 % a [3:0] $end
$var wire 4 & b [3:0] $end
$var wire 2 ' sel [1:0] $end
$var reg 5 ( result [4:0] $end
$upscope $end
$upscope $end
$enddefinitions $end
$comment Show the parameter values. $end
$dumpall
$end
#0
$dumpvars
b1000 (
b0 '
b1010 &
b1100 %
b0 $
b1010 #
b1100 "
b1000 !
$end
#50
b0 !
b0 (
b0 #
b0 &
b1111 "
b1111 %
#100
b1110 !
b1110 (
b1010 #
b1010 &
b1100 "
b1100 %
b1 $
b1 '
#150
b1111 !
b1111 (
b0 #
b0 &
b1111 "
b1111 %
#200
b1000 !
b1000 (
b101 #
b101 &
b11 "
b11 %
b10 $
b10 '
#250
b10000 !
b10000 (
b1 #
b1 &
b1111 "
b1111 %
#300
b101 !
b101 (
b11 #
b11 &
b1000 "
b1000 %
b11 $
b11 '
#350
b11111 !
b11111 (
b10 #
b10 &
b1 "
b1 %
