Full-Adder/fa.v
module fa(

input wire a,
input wire b,
input wire cin,
output wire s,
output wire cout

);

assign s =  (a^b)^cin;
assign cout = (a&b) | (b&cin) | (cin&a);

endmodule

Full-Adder/fa_tb.v
module fa_tb;

reg a, b, cin;
wire s, cout;

fa dut(

.a(a),
.b(b),
.cin(cin),
.s(s),
.cout(cout)

);

initial begin

$dumpfile("test_fa.vcd");
$dumpvars(0, fa_tb);

a = 1'b0;
b = 1'b0;
cin = 1'b0;

#5 a = 1'b0; b = 1'b0; cin = 1'b1;
#5 a = 1'b0; b = 1'b1; cin = 1'b0;
#5 a = 1'b0; b = 1'b1; cin = 1'b1;
#5 a = 1'b1; b = 1'b0; cin = 1'b0;
#5 a = 1'b1; b = 1'b0; cin = 1'b1;
#5 a = 1'b1; b = 1'b1; cin = 1'b0;
#5 a = 1'b1; b = 1'b1; cin = 1'b1;
#5 $finish;

end
endmodule

Full-Adder/test_fa.vcd
$date
	Tue May  6 15:28:57 2025
$end
$version
	Icarus Verilog
$end
$timescale
	1s
$end
$scope module fa_tb $end
$var wire 1 ! s $end
$var wire 1 " cout $end
$var reg 1 # a $end
$var reg 1 $ b $end
$var reg 1 % cin $end
$scope module dut $end
$var wire 1 # a $end
$var wire 1 $ b $end
$var wire 1 % cin $end
$var wire 1 " cout $end
$var wire 1 ! s $end
$upscope $end
$upscope $end
$enddefinitions $end
$comment Show the parameter values. $end
$dumpall
$end
#0
$dumpvars
0%
0$
0#
0"
0!
$end
#5
1!
1%
#10
0%
1$
#15
1"
0!
1%
#20
0"
1!
0%
0$
1#
#25
1"
0!
1%
#30
0%
1$
#35
1!
1%
