8-bit ALU/alu_8bit.v
module alu_8bit(

input wire [7:0] a,
input wire [7:0] b,
input wire  [2:0] sel,
output reg [8:0] result

);

always @(*) begin

case (sel)

	3'b000: result = a & b;         // AND
        3'b001: result = a | b;         // OR
        3'b010: result = a + b;         // ADD
        3'b011: result = a - b;         // SUB
        3'b100: result = a ^ b;         // XOR
        3'b101: result = ~a;            // NOT A
        3'b110: result = a + 1;         // Increment A
        3'b111: result = a - 1;         // Decrement A
        default: result = 8'b00000000;

endcase
end
endmodule

8-bit ALU/alu_8bit_tb.v
module alu_8bit_tb;

reg [7:0] a, b;
reg [2:0] sel;
wire [8:0] result;

alu_8bit dut(

.a(a),
.b(b),
.sel(sel),
.result(result)

);

initial begin

$dumpfile("test_alu_8bit.vcd");
$dumpvars(0, alu_8bit_tb);

// Test Vectors

 a = 8'b10101010; b = 8'b11001100;

    sel = 3'b000; #10;  // AND
    sel = 3'b001; #10;  // OR
    sel = 3'b010; #10;  // ADD
    sel = 3'b011; #10;  // SUB
    sel = 3'b100; #10;  // XOR
    sel = 3'b101; #10;  // NOT A
    sel = 3'b110; #10;  // Increment A
    sel = 3'b111; #10;  // Decrement A
    $finish; #10;

end
endmodule

8-bit ALU/test_alu_8bit.vcd
$date
	Wed May  7 19:43:44 2025
$end
$version
	Icarus Verilog
$end
$timescale
	1s
$end
$scope module alu_8bit_tb $end
$var wire 9 ! result [8:0] $end
$var reg 8 " a [7:0] $end
$var reg 8 # b [7:0] $end
$var reg 3 $ sel [2:0] $end
$scope module dut $end
$var wire 8 % a [7:0] $end
$var wire 8 & b [7:0] $end
$var wire 3 ' sel [2:0] $end
$var reg 9 ( result [8:0] $end
$upscope $end
$upscope $end
$enddefinitions $end
$comment Show the parameter values. $end
$dumpall
$end
#0
$dumpvars
b10001000 (
b0 '
b11001100 &
b10101010 %
b0 $
b11001100 #
b10101010 "
b10001000 !
$end
#10
b11101110 !
b11101110 (
b1 $
b1 '
#20
b101110110 !
b101110110 (
b10 $
b10 '
#30
b111011110 !
b111011110 (
b11 $
b11 '
#40
b1100110 !
b1100110 (
b100 $
b100 '
#50
b101010101 !
b101010101 (
b101 $
b101 '
#60
b10101011 !
b10101011 (
b110 $
b110 '
#70
b10101001 !
b10101001 (
b111 $
b111 '
