2-bit ALU/alu_2bit.v
module alu_2bit(

input [1:0] a,
input [1:0] b,
input [1:0] sel,
output reg [2:0] result // 3 bit to handle overflow ( 2bit + 2bit )

);

always @(*) begin

case ( sel )

2'b00: result = a & b;
2'b01: result = a | b;
2'b10: result = a + b;
2'b11: result = a - b;
default: result = 3'b000;

endcase
end
endmodule

2-bit ALU/alu_2bit_tb.v
module alu_2bit_tb;

reg [1:0] a,b;
reg [1:0] sel;
wire [2:0] result;

alu_2bit dut(

.a(a),
.b(b),
.sel(sel),
.result(result)

);

initial begin

$dumpfile("test_alu_2bit.vcd");
$dumpvars(0, alu_2bit_tb);

    // Test AND operation (sel = 00)
    sel = 2'b00;
    a = 2'b00; b = 2'b00; #5;
    a = 2'b01; b = 2'b10; #5;
    a = 2'b11; b = 2'b10; #5;

    // Test OR operation (sel = 01)
    sel = 2'b01;
    a = 2'b00; b = 2'b01; #5;
    a = 2'b10; b = 2'b10; #5;
    a = 2'b11; b = 2'b00; #5;

    // Test ADD operation (sel = 10)
    sel = 2'b10;
    a = 2'b01; b = 2'b01; #5;  // 1 + 1 = 2
    a = 2'b11; b = 2'b10; #5;  // 3 + 2 = 5

    // Test SUB operation (sel = 11)
    sel = 2'b11;
    a = 2'b10; b = 2'b01; #5;  // 2 - 1 = 1
    a = 2'b00; b = 2'b01; #5;  // 0 - 1 = -1 (2's comp, result = 3'b111)

end
endmodule

2-bit ALU/test_alu_2bit.vcd
$date
	Wed May  7 18:47:16 2025
$end
$version
	Icarus Verilog
$end
$timescale
	1s
$end
$scope module alu_2bit_tb $end
$var wire 3 ! result [2:0] $end
$var reg 2 " a [1:0] $end
$var reg 2 # b [1:0] $end
$var reg 2 $ sel [1:0] $end
$scope module dut $end
$var wire 2 % a [1:0] $end
$var wire 2 & b [1:0] $end
$var wire 2 ' sel [1:0] $end
$var reg 3 ( result [2:0] $end
$upscope $end
$upscope $end
$enddefinitions $end
$comment Show the parameter values. $end
$dumpall
$end
#0
$dumpvars
b0 (
b0 '
b0 &
b0 %
b0 $
b0 #
b0 "
b0 !
$end
#5
b10 #
b10 &
b1 "
b1 %
#10
b10 !
b10 (
b11 "
b11 %
#15
b1 !
b1 (
b1 #
b1 &
b0 "
b0 %
b1 $
b1 '
#20
b10 !
b10 (
b10 #
b10 &
b10 "
b10 %
#25
b11 !
b11 (
b0 #
b0 &
b11 "
b11 %
#30
b10 !
b10 (
b1 #
b1 &
b1 "
b1 %
b10 $
b10 '
#35
b101 !
b101 (
b10 #
b10 &
b11 "
b11 %
#40
b1 !
b1 (
b1 #
b1 &
b10 "
b10 %
b11 $
b11 '
#45
b111 !
b111 (
b0 "
b0 %
