Four_Bit_Comparator/four_bit_comp.v
module four_bit_comp(

input wire [3:0] a,
input wire [3:0] b,
output wire equal,
output wire greater,
output wire less

);

assign equal = ( a==b );
assign greater = ( a>b );
assign less = ( a<b );

endmodule

Four_Bit_Comparator/four_bit_comp_tb.v
module four_bit_comp_tb;

reg a;
reg b;
wire equal;
wire greater;
wire less;

four_bit_comp dut(

.a(a),
.b(b),
.equal(equal),
.greater(greater),
.less(less)

);

initial begin

$dumpfile("test_four_bit_comp.vcd");
$dumpvars(0, four_bit_comp_tb);

a = 4'b0000; b = 4'b0000;

    a = 4'b0000; b = 4'b0000; #5;
    a = 4'b0000; b = 4'b0001; #5;
    a = 4'b0001; b = 4'b0000; #5;
    a = 4'b0010; b = 4'b0010; #5;
    a = 4'b0011; b = 4'b0100; #5;
    a = 4'b0101; b = 4'b0101; #5;
    a = 4'b0110; b = 4'b0111; #5;
    a = 4'b0111; b = 4'b0110; #5;
    a = 4'b1000; b = 4'b1000; #5;
    a = 4'b1001; b = 4'b1010; #5;
    a = 4'b1010; b = 4'b1010; #5;
    a = 4'b1011; b = 4'b1100; #5;
    a = 4'b1100; b = 4'b1100; #5;
    a = 4'b1101; b = 4'b1110; #5;
    a = 4'b1110; b = 4'b1111; #5;
    a = 4'b1111; b = 4'b1111; #5;
    $finish; #5;

end
endmodule

Four_Bit_Comparator/test_four_bit_comp.vcd
$date
	Wed May  7 13:02:34 2025
$end
$version
	Icarus Verilog
$end
$timescale
	1s
$end
$scope module four_bit_comp_tb $end
$var wire 1 ! less $end
$var wire 1 " greater $end
$var wire 1 # equal $end
$var reg 1 $ a $end
$var reg 1 % b $end
$scope module dut $end
$var wire 4 & a [3:0] $end
$var wire 4 ' b [3:0] $end
$var wire 1 ! less $end
$var wire 1 " greater $end
$var wire 1 # equal $end
$upscope $end
$upscope $end
$enddefinitions $end
$comment Show the parameter values. $end
$dumpall
$end
#0
$dumpvars
b0 '
b0 &
0%
0$
1#
0"
0!
$end
#5
0#
1!
b1 '
1%
#10
1"
b0 '
0%
0#
0!
b1 &
1$
#15
1#
0"
b0 &
0$
#20
0#
1"
b1 &
1$
#25
1#
0"
b1 '
1%
#30
0#
1!
b0 &
0$
#35
1"
b0 '
0%
0#
0!
b1 &
1$
#40
1#
0"
b0 &
0$
#45
0#
1"
b1 &
1$
#50
1#
0"
b0 &
0$
#55
0#
1"
b1 &
1$
#60
1#
0"
b0 &
0$
#65
0#
1"
b1 &
1$
#70
1!
b1 '
1%
0#
0"
b0 &
0$
#75
1#
0!
b1 &
1$
