D-Flip-Flop/d_ff.v
module d_ff(

input wire d,
input wire clk,
input wire reset,
output reg y

);

always @(posedge clk or posedge reset) begin

if(reset)
y <= 1'b0;
else
y <= d;

end
endmodule

D-Flip-Flop/d_ff_tb.v
module d_ff_tb;

reg d;
reg clk;
reg reset;
wire y;

d_ff dut(

.d(d),
.clk(clk),
.reset(reset),
.y(y)

);

// clock generation
initial begin
clk = 0;
forever #5 clk = ~clk;
end

// test sequence
initial begin

  $dumpfile("test_d_ff.vcd");
  $dumpvars(0, d_ff_tb);

reset = 1; d = 0;

#12 reset = 0;
 #10 d = 1;
    #10 d = 0;
    #10 d = 1;

    #20 $finish;
end

endmodule

D-Flip-Flop/test_d_ff.vcd
$date
	Tue May  6 18:54:18 2025
$end
$version
	Icarus Verilog
$end
$timescale
	1s
$end
$scope module d_ff_tb $end
$var wire 1 ! y $end
$var reg 1 " clk $end
$var reg 1 # d $end
$var reg 1 $ reset $end
$scope module dut $end
$var wire 1 " clk $end
$var wire 1 # d $end
$var wire 1 $ reset $end
$var reg 1 ! y $end
$upscope $end
$upscope $end
$enddefinitions $end
$comment Show the parameter values. $end
$dumpall
$end
#0
$dumpvars
1$
0#
0"
0!
$end
#5
1"
#10
0"
#12
0$
#15
1"
#20
0"
#22
1#
#25
1!
1"
#30
0"
#32
0#
#35
0!
1"
#40
0"
#42
1#
#45
1!
1"
